CHANGELOG.txt
LICENSE.txt
MANIFEST.in
README.md
credentials_found.txt
main.py
requirements.py
scan_all_internal_ip.py
scan_internal_ip.py
setup.py
ssh_bruteforce.py
test.py
.venv/Lib/site-packages/_virtualenv.py
.venv/Lib/site-packages/BetterPrinting/__init__.py
.venv/Lib/site-packages/BetterPrinting/_main.py
.venv/Lib/site-packages/BetterPrinting/color.py
.venv/Lib/site-packages/BetterPrinting/color_list.py
.venv/Lib/site-packages/BetterPrinting/draw.py
.venv/Lib/site-packages/BetterPrinting/rand.py
.venv/Lib/site-packages/BetterPrinting/system.py
.venv/Lib/site-packages/BetterPrinting/ui.py
.venv/Lib/site-packages/BetterPrinting-0.7.4.dist-info/LICENCE.txt
.venv/Lib/site-packages/BetterPrinting-0.7.4.dist-info/top_level.txt
.venv/Lib/site-packages/PyNaCl-1.5.0.dist-info/top_level.txt
.venv/Lib/site-packages/_distutils_hack/__init__.py
.venv/Lib/site-packages/_distutils_hack/override.py
.venv/Lib/site-packages/bcrypt/__init__.py
.venv/Lib/site-packages/bcrypt-4.3.0.dist-info/top_level.txt
.venv/Lib/site-packages/certifi/__init__.py
.venv/Lib/site-packages/certifi/__main__.py
.venv/Lib/site-packages/certifi/core.py
.venv/Lib/site-packages/certifi-2025.6.15.dist-info/top_level.txt
.venv/Lib/site-packages/cffi/__init__.py
.venv/Lib/site-packages/cffi/_imp_emulation.py
.venv/Lib/site-packages/cffi/_shimmed_dist_utils.py
.venv/Lib/site-packages/cffi/api.py
.venv/Lib/site-packages/cffi/backend_ctypes.py
.venv/Lib/site-packages/cffi/cffi_opcode.py
.venv/Lib/site-packages/cffi/commontypes.py
.venv/Lib/site-packages/cffi/cparser.py
.venv/Lib/site-packages/cffi/error.py
.venv/Lib/site-packages/cffi/ffiplatform.py
.venv/Lib/site-packages/cffi/lock.py
.venv/Lib/site-packages/cffi/model.py
.venv/Lib/site-packages/cffi/pkgconfig.py
.venv/Lib/site-packages/cffi/recompiler.py
.venv/Lib/site-packages/cffi/setuptools_ext.py
.venv/Lib/site-packages/cffi/vengine_cpy.py
.venv/Lib/site-packages/cffi/vengine_gen.py
.venv/Lib/site-packages/cffi/verifier.py
.venv/Lib/site-packages/cffi-1.17.1.dist-info/entry_points.txt
.venv/Lib/site-packages/cffi-1.17.1.dist-info/top_level.txt
.venv/Lib/site-packages/charset_normalizer/__init__.py
.venv/Lib/site-packages/charset_normalizer/__main__.py
.venv/Lib/site-packages/charset_normalizer/api.py
.venv/Lib/site-packages/charset_normalizer/cd.py
.venv/Lib/site-packages/charset_normalizer/constant.py
.venv/Lib/site-packages/charset_normalizer/legacy.py
.venv/Lib/site-packages/charset_normalizer-3.4.2.dist-info/entry_points.txt
.venv/Lib/site-packages/charset_normalizer-3.4.2.dist-info/top_level.txt
.venv/Lib/site-packages/colorama-0.4.6.dist-info/licenses/LICENSE.txt
.venv/Lib/site-packages/idna-3.10.dist-info/LICENSE.md
.venv/Lib/site-packages/paramiko-3.5.1.dist-info/top_level.txt
.venv/Lib/site-packages/pip-23.2.1.dist-info/AUTHORS.txt
.venv/Lib/site-packages/pip-23.2.1.dist-info/LICENSE.txt
.venv/Lib/site-packages/pip-23.2.1.dist-info/entry_points.txt
.venv/Lib/site-packages/pip-23.2.1.dist-info/top_level.txt
.venv/Lib/site-packages/pycparser-2.22.dist-info/top_level.txt
.venv/Lib/site-packages/requests-2.32.4.dist-info/top_level.txt
.venv/Lib/site-packages/setuptools-68.2.0.dist-info/entry_points.txt
.venv/Lib/site-packages/setuptools-68.2.0.dist-info/top_level.txt
.venv/Lib/site-packages/urllib3-2.5.0.dist-info/licenses/LICENSE.txt
.venv/Lib/site-packages/wheel-0.41.2.dist-info/LICENSE.txt
.venv/Lib/site-packages/wheel-0.41.2.dist-info/entry_points.txt
Pytheas22.egg-info/PKG-INFO
Pytheas22.egg-info/SOURCES.txt
Pytheas22.egg-info/dependency_links.txt
Pytheas22.egg-info/requires.txt
Pytheas22.egg-info/top_level.txt
venv/Lib/site-packages/BetterPrinting-0.7.1.dist-info/LICENCE.txt
venv/Lib/site-packages/BetterPrinting-0.7.1.dist-info/top_level.txt
venv/Lib/site-packages/PyNaCl-1.5.0.dist-info/top_level.txt
venv/Lib/site-packages/bcrypt-4.0.1.dist-info/top_level.txt
venv/Lib/site-packages/certifi-2023.5.7.dist-info/top_level.txt
venv/Lib/site-packages/cffi-1.15.1.dist-info/entry_points.txt
venv/Lib/site-packages/cffi-1.15.1.dist-info/top_level.txt
venv/Lib/site-packages/charset_normalizer-3.1.0.dist-info/entry_points.txt
venv/Lib/site-packages/charset_normalizer-3.1.0.dist-info/top_level.txt
venv/Lib/site-packages/colorama-0.4.6.dist-info/licenses/LICENSE.txt
venv/Lib/site-packages/cryptography-41.0.1.dist-info/top_level.txt
venv/Lib/site-packages/idna-3.4.dist-info/LICENSE.md
venv/Lib/site-packages/paramiko-3.2.0.dist-info/top_level.txt
venv/Lib/site-packages/pip-22.3.1.dist-info/LICENSE.txt
venv/Lib/site-packages/pip-22.3.1.dist-info/entry_points.txt
venv/Lib/site-packages/pip-22.3.1.dist-info/top_level.txt
venv/Lib/site-packages/pycparser-2.21.dist-info/top_level.txt
venv/Lib/site-packages/requests-2.31.0.dist-info/top_level.txt
venv/Lib/site-packages/setuptools-65.5.1.dist-info/entry_points.txt
venv/Lib/site-packages/setuptools-65.5.1.dist-info/top_level.txt
venv/Lib/site-packages/urllib3-2.0.2.dist-info/licenses/LICENSE.txt
venv/Lib/site-packages/wheel-0.38.4.dist-info/LICENSE.txt
venv/Lib/site-packages/wheel-0.38.4.dist-info/entry_points.txt
venv/Lib/site-packages/wheel-0.38.4.dist-info/top_level.txt
