Metadata-Version: 2.1
Name: Pytheas22
Version: 0.1.1
Summary: Pytheas22 is a Port Scanner which scans IP-Cameras, internal networks and individual hosts. If the port 22 is open it will try to login to that host via bruteforce
Home-page: 
Author: Fawaz Bashiru
Author-email: fawazbashiru@gmail.com
License: MIT
Keywords: portscanner
Classifier: Development Status :: 6 - Mature
Classifier: Intended Audience :: Education
Classifier: Operating System :: Microsoft :: Windows :: Windows 10
Classifier: License :: OSI Approved :: MIT License
Classifier: Programming Language :: Python :: 3
License-File: LICENSE.txt
Requires-Dist: BetterPrinting
Requires-Dist: colorama
Requires-Dist: paramiko
